waypanel/__init__.py
waypanel/main.py
waypanel/config/cmd.toml
waypanel/config/dockbar.toml
waypanel/config/folders.toml
waypanel/config/gestures.toml
waypanel/config/menu.toml
waypanel/config/panel.toml
waypanel/config/style.css
waypanel/config/t.py
waypanel/config/topbar-launcher.toml
waypanel/config/workspacebar.toml
waypanel/config/scripts/mullvad-connect.py
waypanel/config/scripts/mullvad-disconnect.py
waypanel/config/scripts/mullvad-disconnect.sh
waypanel/config/scripts/mullvad-random-br.py
waypanel/config/scripts/mullvad-status.py
waypanel/config/scripts/mullvad-status.sh
waypanel/config/shaders/revert.shader
waypanel/config/shaders/view-effect.shader
waypanel/config/themes/dark.css
waypanel/config/themes/gruvbox.css
waypanel/config/themes/light.css
waypanel/config/themes/tokyonight.css
waypanel/config/themes/tokyotransparent.css
waypanel/src/panel.py
waypanel/src/core/__init__.py
waypanel/src/core/background.py
waypanel/src/core/create_panel.py
waypanel/src/core/utils.py
waypanel/src/core/shaders/invert
waypanel/src/core/shaders/passthrough
waypanel/src/ipc_server/ipc-async-server.py
waypanel/src/ipc_server/ipc_client.py
waypanel/src/plugins/__init__.py
waypanel/src/plugins/bookmarksPopover.py
waypanel/src/plugins/clipboardMenu.py
waypanel/src/plugins/dashboardBluetooth.py
waypanel/src/plugins/dashboardPopover.py
waypanel/src/plugins/dashboardSoundCard.py
waypanel/src/plugins/dashboardSystem.py
waypanel/src/plugins/dockbar.py
waypanel/src/plugins/folders.py
waypanel/src/plugins/kdeconnect.py
waypanel/src/plugins/launcherMenu.py
waypanel-0.21.0.dist-info/licenses/LICENSE
waypanel-0.21.0.dist-info/METADATA
waypanel-0.21.0.dist-info/WHEEL
waypanel-0.21.0.dist-info/entry_points.txt
waypanel-0.21.0.dist-info/top_level.txt
waypanel-0.21.0.dist-info/RECORD
