Metadata-Version: 2.4
Name: waypanel
Version: 0.21.0
Summary: A Wayfire panel that behaves like a shell
Home-page: https://github.com/killown/waypanel
Author: killown
Author-email: systemofdown@gmail.com
Classifier: Programming Language :: Python :: 3
Classifier: License :: OSI Approved :: MIT License
Classifier: Operating System :: OS Independent
Requires-Python: >=3.6
License-File: LICENSE
Requires-Dist: aiohttp==3.10.5
Requires-Dist: beautifulsoup4==4.12.3
Requires-Dist: netifaces==0.11.0
Requires-Dist: numpy==2.1.0
Requires-Dist: psutil==6.0.0
Requires-Dist: pulsectl==24.4.0
Requires-Dist: Requests==2.32.3
Requires-Dist: setuptools==69.5.1
Requires-Dist: SoundCard==0.4.3
Requires-Dist: toml==0.10.2
Requires-Dist: wayfire
Requires-Dist: pygobject-stubs
Requires-Dist: orjson
Requires-Dist: cffi
Requires-Dist: PyGObject
Requires-Dist: watchdog
Dynamic: author
Dynamic: author-email
Dynamic: classifier
Dynamic: description
Dynamic: description-content-type
Dynamic: home-page
Dynamic: license-file
Dynamic: requires-dist
Dynamic: requires-python
Dynamic: summary
